algebraics-0.2.0.dist-info/METADATA
algebraics-0.2.0.dist-info/WHEEL
algebraics.cpython-36m-x86_64-linux-gnu.so
algebraics-0.2.0.dist-info/RECORD
