Metadata-Version: 2.1
Name: algebraics
Version: 0.2.0
Summary: algebraic numbers library
Keywords: algebraic-numbers arbitrary-precision polynomials real-numbers exact-arithmetic
Author: Jacob Lifshay <programmerjake@gmail.com>
Author-Email: Jacob Lifshay <programmerjake@gmail.com>
License: LGPL-2.1-or-later
